aiuti/__init__.py
aiuti/_version.py
aiuti/asyncio.py
aiuti/filelock.py
aiuti/itertools.py
aiuti/parsing.py
aiuti/py.typed
aiuti/typing.py
aiuti-0.9.2.dist-info/LICENSE
aiuti-0.9.2.dist-info/METADATA
aiuti-0.9.2.dist-info/WHEEL
aiuti-0.9.2.dist-info/top_level.txt
aiuti-0.9.2.dist-info/RECORD
