Metadata-Version: 2.1
Name: aiuti
Version: 0.9.2
Summary: Personal collection of assorted helpers and utilities
Home-page: https://github.com/aiudirog/Aiuti
Author: Roger Aiudi
Author-email: aiudirog@gmail.com
License: MIT
Keywords: utils,helpers,asyncio
Classifier: Development Status :: 3 - Alpha
Classifier: Intended Audience :: Developers
Classifier: License :: OSI Approved :: MIT License
Classifier: Programming Language :: Python :: 3.8
Classifier: Programming Language :: Python :: 3.9
Classifier: Programming Language :: Python :: 3.10
Classifier: Programming Language :: Python :: 3.11
Classifier: Programming Language :: Python :: 3.12
Classifier: Programming Language :: Python :: Implementation :: CPython
Classifier: Programming Language :: Python :: Implementation :: PyPy
Classifier: Topic :: Software Development :: Libraries :: Python Modules
Requires-Python: >=3.8
License-File: LICENSE
